diagnscls/__init__.py
diagnscls/__version__.py
diagnscls/cut_exon.py
diagnscls/input.py
diagnscls-0.0.3.data/scripts/start_with_bam.sh
diagnscls-0.0.3.data/scripts/start_with_fastq.sh
diagnscls-0.0.3.dist-info/METADATA
diagnscls-0.0.3.dist-info/WHEEL
diagnscls-0.0.3.dist-info/top_level.txt
diagnscls-0.0.3.dist-info/RECORD
