Metadata-Version: 2.1
Name: diagnscls
Version: 0.0.3
Summary: diagnosis for non-small cell lung cancer
Home-page: https://github.com/cheymingyu/Biomarker
Author: Mingyu Choi
Author-email: cmg5691@gmail.com
License: UNKNOWN
Platform: UNKNOWN
Classifier: Programming Language :: Python :: 3
Classifier: License :: OSI Approved :: MIT License
Classifier: Operating System :: OS Independent
Requires-Python: >=3.6
